xalc/__init__.py
xalc/formatter.py
xalc/transformer.py
xalc/xalc.py
xalc-0.6.0.dist-info/LICENSE
xalc-0.6.0.dist-info/METADATA
xalc-0.6.0.dist-info/WHEEL
xalc-0.6.0.dist-info/entry_points.txt
xalc-0.6.0.dist-info/top_level.txt
xalc-0.6.0.dist-info/RECORD
