Metadata-Version: 2.1
Name: xalc
Version: 0.6.0
Summary: Hexadecimal calculator
Home-page: https://github.com/rabinv/xalc
Author: Vincent Whitchurch
Author-email: vincent@whitchurch.se
License: MIT
Platform: UNKNOWN
Classifier: Environment :: Console
Classifier: Framework :: IPython
Classifier: Intended Audience :: Developers
Classifier: License :: OSI Approved :: MIT License
Classifier: Programming Language :: Python
Classifier: Topic :: Software Development
Requires-Dist: bitstring (>=3.1.4)
Requires-Dist: blessed (>=1.14.1)
Requires-Dist: ipython (>=5.0.0)
